aiws/__init__.py
aiws/api.py
rlclient/__init__.py
rlclient/client.py
rlclientbdr-1.11.dist-info/LICENSE
rlclientbdr-1.11.dist-info/METADATA
rlclientbdr-1.11.dist-info/WHEEL
rlclientbdr-1.11.dist-info/top_level.txt
rlclientbdr-1.11.dist-info/RECORD
